project_master
