Metadata-Version: 2.1
Name: project-master
Version: 1.2
Summary: This Python script generates a standardized project structure for your Python projects. It creates the necessary folders and files based on your specifications.
Home-page: https://github.com/Armen-Jean-Andreasian
Author: Armen-Jean Andreasian
Author-email: armen_andreasian@proton.me
License: BSD
Keywords: project,directory,python
Classifier: Development Status :: 3 - Alpha
Classifier: Intended Audience :: Developers
Classifier: Topic :: Software Development :: Libraries :: Python Modules
Classifier: Programming Language :: Python :: 3
Classifier: License :: OSI Approved :: BSD License
Classifier: Operating System :: OS Independent
Requires-Python: >=3.8
License-File: LICENSE
